filters/__init__.py
filters/base_filter.py
filters/number_comparison_filter.py
formatters/__init__.py
formatters/append_formatter.py
formatters/base_formatter.py
formatters/capitalize_formatter.py
formatters/join_formatter.py
word-alchemist/__init__.py
word-alchemist/main.py
word-alchemist/word_alchemist.py
word-alchemist/filters/__init__.py
word-alchemist/filters/base_filter.py
word-alchemist/filters/number_comparison_filter.py
word-alchemist/formatters/__init__.py
word-alchemist/formatters/append_formatter.py
word-alchemist/formatters/base_formatter.py
word-alchemist/formatters/capitalize_formatter.py
word-alchemist/formatters/join_formatter.py
word_alchemist/__init__.py
word_alchemist/main.py
word_alchemist/word_alchemist.py
word_alchemist/filters/__init__.py
word_alchemist/filters/base_filter.py
word_alchemist/filters/number_comparison_filter.py
word_alchemist/formatters/__init__.py
word_alchemist/formatters/append_formatter.py
word_alchemist/formatters/base_formatter.py
word_alchemist/formatters/capitalize_formatter.py
word_alchemist/formatters/join_formatter.py
word_alchemist/parsers/__init__.py
word_alchemist/parsers/filter_parser.py
word_alchemist/parsers/json_parser.py
word_alchemist-0.1.0.dist-info/LICENSE
word_alchemist-0.1.0.dist-info/METADATA
word_alchemist-0.1.0.dist-info/WHEEL
word_alchemist-0.1.0.dist-info/entry_points.txt
word_alchemist-0.1.0.dist-info/top_level.txt
word_alchemist-0.1.0.dist-info/RECORD
