Metadata-Version: 2.1
Name: word-alchemist
Version: 0.1.0
Summary: Simple Python CLI to help you brainstorm the name of your next product, studio, brand etc
Home-page: https://github.com/cckelly/word-alchemist
Author: Charles Kelly
License: MIT
Requires-Python: >=3.6
License-File: LICENSE
Requires-Dist: syllapy
